talisman_ie_datamodel-0.6.18.data/data/VERSION
tie_datamodel/__init__.py
tie_datamodel/env.py
tie_datamodel/datamodel/__init__.py
tie_datamodel/datamodel/container.py
tie_datamodel/datamodel/helpers.py
tie_datamodel/datamodel/node/__init__.py
tie_datamodel/datamodel/node/node_converter.py
tie_datamodel/datamodel/node/table/__init__.py
tie_datamodel/datamodel/node/table/abstract.py
tie_datamodel/datamodel/node/table/markup.py
tie_datamodel/datamodel/node/table/node.py
tie_datamodel/datamodel/node/table/table_view.py
tie_datamodel/datamodel/node/text/__init__.py
tie_datamodel/datamodel/node/text/abstract.py
tie_datamodel/datamodel/node/text/markup.py
tie_datamodel/datamodel/node/text/model.py
tie_datamodel/datamodel/node/text/node.py
tie_datamodel/datamodel/node/text/chain/__init__.py
tie_datamodel/datamodel/node/text/chain/impl.py
tie_datamodel/datamodel/node/text/chain/mention.py
tie_datamodel/datamodel/node/text/chain/model.py
tie_datamodel/datamodel/node/text/sentence/__init__.py
tie_datamodel/datamodel/node/text/sentence/impl.py
tie_datamodel/datamodel/node/text/sentence/model.py
tie_datamodel/datamodel/span/__init__.py
tie_datamodel/datamodel/span/abstract.py
tie_datamodel/datamodel/span/default.py
tie_datamodel/datamodel/span/nullable.py
tie_datamodel/datamodel/span/span.py
tie_datamodel/datamodel/span/token.py
tie_datamodel/dataset/__init__.py
tie_datamodel/dataset/split_tdm_data.py
tie_datamodel/dataset/tdm_dataset_manager.py
tie_datamodel/dataset/versioned_tdm_dataset_manager.py
tie_datamodel/readers/__init__.py
tie_datamodel/readers/brat.py
tie_datamodel/readers/directory.py
tie_datamodel/readers/docred.py
tie_datamodel/readers/labelstudio.py
tie_datamodel/readers/raw.py
tie_datamodel/readers/readers.py
tie_datamodel/readers/rucoco.py
tie_datamodel/readers/rueval.py
tie_datamodel/readers/tacred.py
tie_datamodel/readers/conll/__init__.py
tie_datamodel/readers/conll/abstract.py
tie_datamodel/readers/conll/common.py
tie_datamodel/readers/conll/ontonotes.py
talisman_ie_datamodel-0.6.18.dist-info/METADATA
talisman_ie_datamodel-0.6.18.dist-info/WHEEL
talisman_ie_datamodel-0.6.18.dist-info/entry_points.txt
talisman_ie_datamodel-0.6.18.dist-info/top_level.txt
talisman_ie_datamodel-0.6.18.dist-info/RECORD
