Metadata-Version: 2.4
Name: talisman-ie-datamodel
Version: 0.6.18
Summary: Talisman-IE Document Model
Author: ISPRAS Talisman NLP team
Author-email: modis@ispras.ru
Maintainer: Vladimir Mayorov
Maintainer-email: vmayorov@ispras.ru
License: Apache Software License
Classifier: Development Status :: 3 - Alpha
Classifier: Programming Language :: Python :: 3
Classifier: Programming Language :: Python :: 3.10
Classifier: Intended Audience :: Developers
Classifier: Operating System :: OS Independent
Classifier: License :: OSI Approved :: Apache Software License
Requires-Python: >=3.10
Requires-Dist: talisman-interfaces<0.12,>=0.11.9
Requires-Dist: talisman-dm<2,>=1.3.4
Requires-Dist: immutabledict<3,>=2.2.4
Requires-Dist: intervaltree~=3.1
Requires-Dist: pydantic~=2.5
Requires-Dist: typing_extensions>=4.0.0
Requires-Dist: aiofiles>=24.1.0
Provides-Extra: tests
Requires-Dist: talisman-tools; extra == "tests"
Dynamic: author
Dynamic: author-email
Dynamic: classifier
Dynamic: description-content-type
Dynamic: license
Dynamic: maintainer
Dynamic: maintainer-email
Dynamic: provides-extra
Dynamic: requires-dist
Dynamic: requires-python
Dynamic: summary
